syspect/__init__.py
syspect/cli.py
syspect/demo_runner.py
syspect/engine.py
syspect/insights.py
syspect/rule_registry.py
syspect/collectors/__init__.py
syspect/collectors/basic.py
syspect/collectors/container.py
syspect/collectors/web.py
syspect/rules/__init__.py
syspect/rules/cpu_usage.py
syspect/rules/missing_config.py
syspect/rules/stale_mount.py
syspect/utils/__init__.py
syspect/utils/custom_loader.py
syspect-0.1.0.dist-info/licenses/LICENSE
syspect-0.1.0.dist-info/METADATA
syspect-0.1.0.dist-info/WHEEL
syspect-0.1.0.dist-info/entry_points.txt
syspect-0.1.0.dist-info/top_level.txt
syspect-0.1.0.dist-info/RECORD
