Metadata-Version: 2.4
Name: syspect
Version: 0.1.0
Summary: A lightweight, modular diagnostic rule engine to help your Python apps introspect and explain system issues — like a built-in sysadmin.
Author-email: Rahul Sharma <rahulxsh@gmail.com>
Maintainer-email: Rahul Sharma <rahulxsh@gmail.com>
License: MIT
Project-URL: Homepage, https://github.com/rahulXs/syspect
Project-URL: Documentation, https://github.com/rahulXs/syspect#readme
Project-URL: Issues, https://github.com/rahulXs/syspect/issues
Project-URL: Source, https://github.com/rahulXs/syspect
Keywords: diagnostics,rule-engine,system-monitoring,cli,observability,python-tools
Classifier: Programming Language :: Python :: 3
Classifier: License :: OSI Approved :: MIT License
Classifier: Operating System :: OS Independent
Classifier: Development Status :: 4 - Beta
Classifier: Intended Audience :: Developers
Classifier: Topic :: Software Development :: Build Tools
Classifier: Topic :: System :: Monitoring
Requires-Python: >=3.8
License-File: LICENSE
Requires-Dist: click>=8.0
Requires-Dist: psutil>=5.9.0
Dynamic: license-file
